LICENSE
README.rst
setup.py
validation/__init__.py
validation/common.py
validation/core.py
validation/core.pyi
validation/datastructure.py
validation/datastructure.pyi
validation/datetime.py
validation/datetime.pyi
validation/email.py
validation/email.pyi
validation/number.py
validation/number.pyi
validation/py.typed
validation/string.py
validation/string.pyi
validation/uuid.py
validation/uuid.pyi
validation/tests/__init__.py
validation/tests/test_bool.py
validation/tests/test_bytes.py
validation/tests/test_date.py
validation/tests/test_datetime.py
validation/tests/test_email.py
validation/tests/test_float.py
validation/tests/test_int.py
validation/tests/test_list.py
validation/tests/test_mapping.py
validation/tests/test_optional_argument.py
validation/tests/test_set.py
validation/tests/test_structure.py
validation/tests/test_text.py
validation/tests/test_timedelta.py
validation/tests/test_tuple.py
validation/tests/test_uuid.py